{
	"name": "SQLChargesRefunds",
	"properties": {
		"linkedServiceName": {
			"referenceName": "AzureSqlDatabaseRAW_ATLFS_DATA",
			"type": "LinkedServiceReference"
		},
		"annotations": [],
		"type": "AzureSqlTable",
		"schema": [
			{
				"name": "_sdc_batched_at",
				"type": "nvarchar"
			},
			{
				"name": "_sdc_level_0_id",
				"type": "nvarchar"
			},
			{
				"name": "_sdc_received_at",
				"type": "nvarchar"
			},
			{
				"name": "_sdc_sequence",
				"type": "nvarchar"
			},
			{
				"name": "_sdc_source_key_id",
				"type": "nvarchar"
			},
			{
				"name": "_sdc_table_version",
				"type": "nvarchar"
			},
			{
				"name": "amount",
				"type": "int",
				"precision": 10
			},
			{
				"name": "balance_transaction",
				"type": "nvarchar"
			},
			{
				"name": "charge",
				"type": "nvarchar"
			},
			{
				"name": "created",
				"type": "int",
				"precision": 10
			},
			{
				"name": "currency",
				"type": "nvarchar"
			},
			{
				"name": "id",
				"type": "nvarchar"
			},
			{
				"name": "metadata__websiteId",
				"type": "nvarchar"
			},
			{
				"name": "object",
				"type": "nvarchar"
			},
			{
				"name": "payment_intent",
				"type": "nvarchar"
			},
			{
				"name": "reason",
				"type": "nvarchar"
			},
			{
				"name": "receipt_number",
				"type": "nvarchar"
			},
			{
				"name": "status",
				"type": "nvarchar"
			}
		],
		"typeProperties": {
			"schema": "dbo",
			"table": "FINANCE_STRIPE_charges__refunds"
		}
	},
	"type": "Microsoft.DataFactory/factories/datasets"
}